sphinx_click/rst_to_ansi_formatter/__init__.py
sphinx_click/rst_to_ansi_formatter/colors.py
sphinx_click/rst_to_ansi_formatter/formatter.py
sphinx_click/rst_to_ansi_formatter/py.typed
sphinx_click/rst_to_ansi_formatter/textutils.py
sphinx_click/rst_to_ansi_formatter/types.py
sphinx_click_rst_to_ansi_formatter-0.1.5.dist-info/LICENSE
sphinx_click_rst_to_ansi_formatter-0.1.5.dist-info/METADATA
sphinx_click_rst_to_ansi_formatter-0.1.5.dist-info/WHEEL
sphinx_click_rst_to_ansi_formatter-0.1.5.dist-info/RECORD
